SydneyGPT/SydneyGPT.py
SydneyGPT/SydneyGPTUtils.py
SydneyGPT/__init__.py
SydneyGPT/conversation_style.py
SydneyGPT/main.py
SydneyGPT-0.13.2.dist-info/LICENSE
SydneyGPT-0.13.2.dist-info/METADATA
SydneyGPT-0.13.2.dist-info/WHEEL
SydneyGPT-0.13.2.dist-info/entry_points.txt
SydneyGPT-0.13.2.dist-info/top_level.txt
SydneyGPT-0.13.2.dist-info/RECORD
