Metadata-Version: 2.1
Name: SydneyGPT
Version: 0.13.2
Summary: Reverse engineered Sydney Bing Chat API
Home-page: https://github.com/rafaelcalleja/SydneyGPT
Author: Rafael Calleja
Author-email: rafaelcalleja@gmail.com
License: GNU General Public License v2.0
Project-URL: Bug Report, https://github.com/rafaelcalleja/SydneyGPT/issues/new
Classifier: License :: OSI Approved :: The Unlicense (Unlicense)
Classifier: Intended Audience :: Developers
Classifier: Topic :: Software Development :: Libraries :: Python Modules
Classifier: Programming Language :: Python :: 3.10
Classifier: Programming Language :: Python :: 3.11
License-File: LICENSE
Requires-Dist: EdgeGPT >=0.8.2
